newscatcher_catchall/__init__.py
newscatcher_catchall/client.py
newscatcher_catchall/core/__init__.py
newscatcher_catchall/core/api_error.py
newscatcher_catchall/core/client_wrapper.py
newscatcher_catchall/core/datetime_utils.py
newscatcher_catchall/core/file.py
newscatcher_catchall/core/force_multipart.py
newscatcher_catchall/core/http_client.py
newscatcher_catchall/core/http_response.py
newscatcher_catchall/core/http_sse/__init__.py
newscatcher_catchall/core/http_sse/_api.py
newscatcher_catchall/core/http_sse/_decoders.py
newscatcher_catchall/core/http_sse/_exceptions.py
newscatcher_catchall/core/http_sse/_models.py
newscatcher_catchall/core/jsonable_encoder.py
newscatcher_catchall/core/pydantic_utilities.py
newscatcher_catchall/core/query_encoder.py
newscatcher_catchall/core/remove_none_from_dict.py
newscatcher_catchall/core/request_options.py
newscatcher_catchall/core/serialization.py
newscatcher_catchall/environment.py
newscatcher_catchall/errors/__init__.py
newscatcher_catchall/errors/bad_request_error.py
newscatcher_catchall/errors/forbidden_error.py
newscatcher_catchall/errors/not_found_error.py
newscatcher_catchall/errors/unprocessable_entity_error.py
newscatcher_catchall/jobs/__init__.py
newscatcher_catchall/jobs/client.py
newscatcher_catchall/jobs/raw_client.py
newscatcher_catchall/meta/__init__.py
newscatcher_catchall/meta/client.py
newscatcher_catchall/meta/raw_client.py
newscatcher_catchall/meta/types/__init__.py
newscatcher_catchall/meta/types/get_version_response.py
newscatcher_catchall/meta/types/health_check_response.py
newscatcher_catchall/monitors/__init__.py
newscatcher_catchall/monitors/client.py
newscatcher_catchall/monitors/raw_client.py
newscatcher_catchall/monitors/types/__init__.py
newscatcher_catchall/monitors/types/disable_monitor_response.py
newscatcher_catchall/monitors/types/enable_monitor_response.py
newscatcher_catchall/monitors/types/list_monitor_jobs_request_sort.py
newscatcher_catchall_sdk-0.4.1.dist-info/LICENSE
newscatcher_catchall_sdk-0.4.1.dist-info/METADATA
newscatcher_catchall_sdk-0.4.1.dist-info/WHEEL
newscatcher_catchall_sdk-0.4.1.dist-info/RECORD
